{"schemaVersion":1,"graphVersion":"modern-2000-v2026.10.0","sourceVersion":"v2026.10.0","drivers":[{"id":"adrian-sutil","givenName":"Adrian","familyName":"Sutil","name":"Adrian Sutil","activeFrom":2007,"activeTo":2014,"componentId":0},{"id":"alex-yoong","givenName":"Alex","familyName":"Yoong","name":"Alexander Charles Yoong Loong","activeFrom":2001,"activeTo":2002,"componentId":0},{"id":"alexander-albon","givenName":"Alexander","familyName":"Albon","name":"Alexander Philippe Albon Ansusinha","activeFrom":2019,"activeTo":2026,"componentId":0},{"id":"alexander-rossi","givenName":"Alexander","familyName":"Rossi","name":"Alexander Michael Rossi","activeFrom":2015,"activeTo":2015,"componentId":0},{"id":"alexander-wurz","givenName":"Alexander","familyName":"Wurz","name":"Alexander Georg Wurz","activeFrom":2000,"activeTo":2007,"componentId":0},{"id":"allan-mcnish","givenName":"Allan","familyName":"McNish","name":"Allan McNish","activeFrom":2002,"activeTo":2002,"componentId":1},{"id":"andre-lotterer","givenName":"André","familyName":"Lotterer","name":"André Lotterer","activeFrom":2014,"activeTo":2014,"componentId":0},{"id":"anthony-davidson","givenName":"Anthony","familyName":"Davidson","name":"Anthony Denis Davidson","activeFrom":2002,"activeTo":2008,"componentId":0},{"id":"antonio-giovinazzi","givenName":"Antonio","familyName":"Giovinazzi","name":"Antonio Maria Giovinazzi","activeFrom":2017,"activeTo":2021,"componentId":0},{"id":"antonio-pizzonia","givenName":"Antônio","familyName":"Pizzonia","name":"Antônio Reginaldo Pizzonia Júnior","activeFrom":2003,"activeTo":2005,"componentId":0},{"id":"arvid-lindblad","givenName":"Arvid","familyName":"Lindblad","name":"Arvid Anand Olof Lindblad","activeFrom":2026,"activeTo":2026,"componentId":0},{"id":"brendon-hartley","givenName":"Brendon","familyName":"Hartley","name":"Brendon Morris Hartley","activeFrom":2017,"activeTo":2018,"componentId":0},{"id":"bruno-senna","givenName":"Bruno","familyName":"Senna","name":"Bruno Senna Lalli","activeFrom":2010,"activeTo":2012,"componentId":0},{"id":"carlos-sainz-jr","givenName":"Carlos","familyName":"Sainz Jr.","name":"Carlos Sainz Vázquez de Castro","activeFrom":2015,"activeTo":2026,"componentId":0},{"id":"charles-leclerc","givenName":"Charles","familyName":"Leclerc","name":"Charles Marc Hervé Perceval Leclerc","activeFrom":2018,"activeTo":2026,"componentId":0},{"id":"charles-pic","givenName":"Charles","familyName":"Pic","name":"Charles Maurice Marcel Pic","activeFrom":2012,"activeTo":2013,"componentId":0},{"id":"christian-klien","givenName":"Christian","familyName":"Klien","name":"Christian Klien","activeFrom":2004,"activeTo":2010,"componentId":0},{"id":"christijan-albers","givenName":"Christijan","familyName":"Albers","name":"Christijan Albers","activeFrom":2005,"activeTo":2007,"componentId":0},{"id":"cristiano-da-matta","givenName":"Cristiano","familyName":"Da Matta","name":"Cristiano Monteiro da Matta","activeFrom":2003,"activeTo":2004,"componentId":0},{"id":"daniel-ricciardo","givenName":"Daniel","familyName":"Ricciardo","name":"Daniel Joseph Ricciardo","activeFrom":2011,"activeTo":2024,"componentId":0},{"id":"daniil-kvyat","givenName":"Daniil","familyName":"Kvyat","name":"Daniil Vyacheslavovich Kvyat","activeFrom":2014,"activeTo":2020,"componentId":0},{"id":"david-coulthard","givenName":"David","familyName":"Coulthard","name":"David Marshall Coulthard","activeFrom":2000,"activeTo":2008,"componentId":0},{"id":"eddie-irvine","givenName":"Eddie","familyName":"Irvine","name":"Edmund Irvine Jr.","activeFrom":2000,"activeTo":2002,"componentId":0},{"id":"enrique-bernoldi","givenName":"Enrique","familyName":"Bernoldi","name":"Enrique Antônio Langue e Silvério de Bernoldi","activeFrom":2001,"activeTo":2002,"componentId":0},{"id":"esteban-gutierrez","givenName":"Esteban","familyName":"Gutiérrez","name":"Esteban Manuel Gutiérrez Gutiérrez","activeFrom":2013,"activeTo":2016,"componentId":0},{"id":"esteban-ocon","givenName":"Esteban","familyName":"Ocon","name":"Esteban José Jean-Pierre Ocon-Khelfane","activeFrom":2016,"activeTo":2026,"componentId":0},{"id":"felipe-massa","givenName":"Felipe","familyName":"Massa","name":"Felipe Massa","activeFrom":2002,"activeTo":2017,"componentId":0},{"id":"felipe-nasr","givenName":"Felipe","familyName":"Nasr","name":"Luiz Felipe de Oliveira Nasr","activeFrom":2015,"activeTo":2016,"componentId":0},{"id":"fernando-alonso","givenName":"Fernando","familyName":"Alonso","name":"Fernando Alonso Díaz","activeFrom":2001,"activeTo":2026,"componentId":0},{"id":"franck-montagny","givenName":"Franck","familyName":"Montagny","name":"Franck Montagny","activeFrom":2006,"activeTo":2006,"componentId":0},{"id":"franco-colapinto","givenName":"Franco","familyName":"Colapinto","name":"Franco Alejandro Colapinto","activeFrom":2024,"activeTo":2026,"componentId":0},{"id":"gabriel-bortoleto","givenName":"Gabriel","familyName":"Bortoleto","name":"Gabriel Lourenzo Bortoleto Oliveira","activeFrom":2025,"activeTo":2026,"componentId":0},{"id":"gaston-mazzacane","givenName":"Gastón","familyName":"Mazzacane","name":"Gastón Hugo Mazzacane","activeFrom":2000,"activeTo":2001,"componentId":0},{"id":"george-russell","givenName":"George","familyName":"Russell","name":"George William Russell","activeFrom":2019,"activeTo":2026,"componentId":0},{"id":"giancarlo-fisichella","givenName":"Giancarlo","familyName":"Fisichella","name":"Giancarlo Fisichella","activeFrom":2000,"activeTo":2009,"componentId":0},{"id":"gianmaria-bruni","givenName":"Gianmaria","familyName":"Bruni","name":"Gianmaria Bruni","activeFrom":2004,"activeTo":2004,"componentId":0},{"id":"giedo-van-der-garde","givenName":"Giedo","familyName":"Van der Garde","name":"Giedo Gijsbertus Gerrit van der Garde","activeFrom":2013,"activeTo":2013,"componentId":0},{"id":"giorgio-pantano","givenName":"Giorgio","familyName":"Pantano","name":"Giorgio Pantano","activeFrom":2004,"activeTo":2004,"componentId":0},{"id":"guanyu-zhou","givenName":"Guanyu","familyName":"Zhou","name":"Guanyu Zhou","activeFrom":2022,"activeTo":2024,"componentId":0},{"id":"heikki-kovalainen","givenName":"Heikki","familyName":"Kovalainen","name":"Heikki Johannes Kovalainen","activeFrom":2007,"activeTo":2013,"componentId":0},{"id":"heinz-harald-frentzen","givenName":"Heinz-Harald","familyName":"Frentzen","name":"Heinz-Harald Frentzen","activeFrom":2000,"activeTo":2003,"componentId":0},{"id":"isack-hadjar","givenName":"Isack","familyName":"Hadjar","name":"Isack Alexandre Hadjar","activeFrom":2025,"activeTo":2026,"componentId":0},{"id":"jack-aitken","givenName":"Jack","familyName":"Aitken","name":"Jack Anthony Han-Aitken","activeFrom":2020,"activeTo":2020,"componentId":0},{"id":"jack-doohan","givenName":"Jack","familyName":"Doohan","name":"Jack Michael Doohan","activeFrom":2024,"activeTo":2025,"componentId":0},{"id":"jacques-villeneuve","givenName":"Jacques","familyName":"Villeneuve","name":"Jacques Joseph Charles Villeneuve","activeFrom":2000,"activeTo":2006,"componentId":0},{"id":"jaime-alguersuari","givenName":"Jaime","familyName":"Alguersuari","name":"Jaime Víctor Alguersuari Escudero","activeFrom":2009,"activeTo":2011,"componentId":0},{"id":"jarno-trulli","givenName":"Jarno","familyName":"Trulli","name":"Jarno Trulli","activeFrom":2000,"activeTo":2011,"componentId":0},{"id":"jean-alesi","givenName":"Jean","familyName":"Alesi","name":"Jean Robert Alesi","activeFrom":2000,"activeTo":2001,"componentId":0},{"id":"jean-eric-vergne","givenName":"Jean-Éric","familyName":"Vergne","name":"Jean-Éric Serge Raymond Vergne","activeFrom":2012,"activeTo":2014,"componentId":0},{"id":"jenson-button","givenName":"Jenson","familyName":"Button","name":"Jenson Alexander Lyons Button","activeFrom":2000,"activeTo":2017,"componentId":0},{"id":"jerome-dambrosio","givenName":"Jérôme","familyName":"D'Ambrosio","name":"Jérôme d'Ambrosio","activeFrom":2011,"activeTo":2012,"componentId":0},{"id":"johnny-herbert","givenName":"Johnny","familyName":"Herbert","name":"John Paul Herbert","activeFrom":2000,"activeTo":2000,"componentId":0},{"id":"jolyon-palmer","givenName":"Jolyon","familyName":"Palmer","name":"Jolyon Carlyle Palmer","activeFrom":2016,"activeTo":2017,"componentId":0},{"id":"jos-verstappen","givenName":"Jos","familyName":"Verstappen","name":"Johannes Franciscus Verstappen","activeFrom":2000,"activeTo":2003,"componentId":0},{"id":"juan-pablo-montoya","givenName":"Juan Pablo","familyName":"Montoya","name":"Juan Pablo Montoya Roldán","activeFrom":2001,"activeTo":2006,"componentId":0},{"id":"jules-bianchi","givenName":"Jules","familyName":"Bianchi","name":"Jules Lucien André Bianchi","activeFrom":2013,"activeTo":2014,"componentId":2},{"id":"justin-wilson","givenName":"Justin","familyName":"Wilson","name":"Justin Boyd Wilson","activeFrom":2003,"activeTo":2003,"componentId":0},{"id":"kamui-kobayashi","givenName":"Kamui","familyName":"Kobayashi","name":"Kamui Kobayashi","activeFrom":2009,"activeTo":2014,"componentId":0},{"id":"karun-chandhok","givenName":"Karun","familyName":"Chandhok","name":"Karun Chandhok","activeFrom":2010,"activeTo":2011,"componentId":0},{"id":"kazuki-nakajima","givenName":"Kazuki","familyName":"Nakajima","name":"Kazuki Nakajima","activeFrom":2007,"activeTo":2009,"componentId":0},{"id":"kevin-magnussen","givenName":"Kevin","familyName":"Magnussen","name":"Kevin Jan Magnussen","activeFrom":2014,"activeTo":2024,"componentId":0},{"id":"kimi-antonelli","givenName":"Kimi","familyName":"Antonelli","name":"Andrea Kimi Antonelli","activeFrom":2025,"activeTo":2026,"componentId":0},{"id":"kimi-raikkonen","givenName":"Kimi","familyName":"Räikkönen","name":"Kimi-Matias Räikkönen","activeFrom":2001,"activeTo":2021,"componentId":0},{"id":"lance-stroll","givenName":"Lance","familyName":"Stroll","name":"Lance Strulovitch","activeFrom":2017,"activeTo":2026,"componentId":0},{"id":"lando-norris","givenName":"Lando","familyName":"Norris","name":"Lando Norris","activeFrom":2019,"activeTo":2026,"componentId":0},{"id":"lewis-hamilton","givenName":"Lewis","familyName":"Hamilton","name":"Lewis Carl Davidson Hamilton","activeFrom":2007,"activeTo":2026,"componentId":0},{"id":"liam-lawson","givenName":"Liam","familyName":"Lawson","name":"Liam Jared Lawson","activeFrom":2023,"activeTo":2026,"componentId":0},{"id":"logan-sargeant","givenName":"Logan","familyName":"Sargeant","name":"Logan Hunter Sargeant","activeFrom":2023,"activeTo":2024,"componentId":0},{"id":"luca-badoer","givenName":"Luca","familyName":"Badoer","name":"Luca Badoer","activeFrom":2009,"activeTo":2009,"componentId":0},{"id":"lucas-di-grassi","givenName":"Lucas","familyName":"Di Grassi","name":"Lucas Tucci di Grassi","activeFrom":2010,"activeTo":2010,"componentId":0},{"id":"luciano-burti","givenName":"Luciano","familyName":"Burti","name":"Luciano Pucci Burti","activeFrom":2000,"activeTo":2001,"componentId":0},{"id":"marc-gene","givenName":"Marc","familyName":"Gené","name":"Marc Gené i Guerrero","activeFrom":2000,"activeTo":2004,"componentId":0},{"id":"marcus-ericsson","givenName":"Marcus","familyName":"Ericsson","name":"Marcus Thorbjörn Ericsson","activeFrom":2014,"activeTo":2018,"componentId":0},{"id":"mark-webber","givenName":"Mark","familyName":"Webber","name":"Mark Alan Webber","activeFrom":2002,"activeTo":2013,"componentId":0},{"id":"markus-winkelhock","givenName":"Markus","familyName":"Winkelhock","name":"Markus Winkelhock","activeFrom":2007,"activeTo":2007,"componentId":0},{"id":"max-chilton","givenName":"Max","familyName":"Chilton","name":"Maximilian Alexander Chilton","activeFrom":2013,"activeTo":2014,"componentId":2},{"id":"max-verstappen","givenName":"Max","familyName":"Verstappen","name":"Max Emilian Verstappen","activeFrom":2015,"activeTo":2026,"componentId":0},{"id":"michael-schumacher","givenName":"Michael","familyName":"Schumacher","name":"Michael Schumacher","activeFrom":2000,"activeTo":2012,"componentId":0},{"id":"mick-schumacher","givenName":"Mick","familyName":"Schumacher","name":"Mick Schumacher","activeFrom":2021,"activeTo":2022,"componentId":0},{"id":"mika-hakkinen","givenName":"Mika","familyName":"Häkkinen","name":"Mika Pauli Häkkinen","activeFrom":2000,"activeTo":2001,"componentId":0},{"id":"mika-salo","givenName":"Mika","familyName":"Salo","name":"Mika Juhani Salo","activeFrom":2000,"activeTo":2002,"componentId":1},{"id":"narain-karthikeyan","givenName":"Narain","familyName":"Karthikeyan","name":"Kumar Ram Narain Karthikeyan","activeFrom":2005,"activeTo":2012,"componentId":0},{"id":"nelson-piquet-jr","givenName":"Nelson","familyName":"Piquet Jr.","name":"Nelson Ângelo Tamsma Piquet Souto Maior","activeFrom":2008,"activeTo":2009,"componentId":0},{"id":"nicholas-latifi","givenName":"Nicholas","familyName":"Latifi","name":"Nicholas Daniel Latifi","activeFrom":2020,"activeTo":2022,"componentId":0},{"id":"nick-heidfeld","givenName":"Nick","familyName":"Heidfeld","name":"Nick Lars Heidfeld","activeFrom":2000,"activeTo":2011,"componentId":0},{"id":"nico-hulkenberg","givenName":"Nico","familyName":"Hülkenberg","name":"Nicolas Hülkenberg","activeFrom":2010,"activeTo":2026,"componentId":0},{"id":"nico-rosberg","givenName":"Nico","familyName":"Rosberg","name":"Nico Erik Rosberg","activeFrom":2006,"activeTo":2016,"componentId":0},{"id":"nicolas-kiesa","givenName":"Nicolas","familyName":"Kiesa","name":"Nicolas Kiesa","activeFrom":2003,"activeTo":2003,"componentId":0},{"id":"nikita-mazepin","givenName":"Nikita","familyName":"Mazepin","name":"Nikita Dmitriyevich Mazepin","activeFrom":2021,"activeTo":2021,"componentId":0},{"id":"nyck-de-vries","givenName":"Nyck","familyName":"De Vries","name":"Hendrik Johannes Nicasius de Vries","activeFrom":2022,"activeTo":2023,"componentId":0},{"id":"oliver-bearman","givenName":"Oliver","familyName":"Bearman","name":"Oliver James Bearman","activeFrom":2024,"activeTo":2026,"componentId":0},{"id":"olivier-panis","givenName":"Olivier","familyName":"Panis","name":"Olivier Jean Denis Marie Panis","activeFrom":2001,"activeTo":2004,"componentId":0},{"id":"oscar-piastri","givenName":"Oscar","familyName":"Piastri","name":"Oscar Jack Piastri","activeFrom":2023,"activeTo":2026,"componentId":0},{"id":"pascal-wehrlein","givenName":"Pascal","familyName":"Wehrlein","name":"Pascal Konrad Wehrlein","activeFrom":2016,"activeTo":2017,"componentId":0},{"id":"pastor-maldonado","givenName":"Pastor","familyName":"Maldonado","name":"Pastor Rafael Maldonado Motta","activeFrom":2011,"activeTo":2015,"componentId":0},{"id":"patrick-friesacher","givenName":"Patrick","familyName":"Friesacher","name":"Patrick Friesacher","activeFrom":2005,"activeTo":2005,"componentId":0},{"id":"paul-di-resta","givenName":"Paul","familyName":"Di Resta","name":"Paul di Resta","activeFrom":2011,"activeTo":2017,"componentId":0},{"id":"pedro-de-la-rosa","givenName":"Pedro","familyName":"De la Rosa","name":"Pedro Martínez de la Rosa","activeFrom":2000,"activeTo":2012,"componentId":0},{"id":"pedro-diniz","givenName":"Pedro","familyName":"Diniz","name":"Pedro Paulo Falleiros dos Santos Diniz","activeFrom":2000,"activeTo":2000,"componentId":1},{"id":"pierre-gasly","givenName":"Pierre","familyName":"Gasly","name":"Pierre Jean-Jacques Gasly","activeFrom":2017,"activeTo":2026,"componentId":0},{"id":"pietro-fittipaldi","givenName":"Pietro","familyName":"Fittipaldi","name":"Pietro Fittipaldi da Cruz","activeFrom":2020,"activeTo":2020,"componentId":0},{"id":"ralf-schumacher","givenName":"Ralf","familyName":"Schumacher","name":"Ralf Schumacher","activeFrom":2000,"activeTo":2007,"componentId":0},{"id":"ralph-firman","givenName":"Ralph","familyName":"Firman","name":"Ralph David Firman Jr.","activeFrom":2003,"activeTo":2003,"componentId":0},{"id":"ricardo-zonta","givenName":"Ricardo","familyName":"Zonta","name":"Ricardo Luiz Zonta","activeFrom":2000,"activeTo":2005,"componentId":0},{"id":"rio-haryanto","givenName":"Rio","familyName":"Haryanto","name":"Rio Haryanto","activeFrom":2016,"activeTo":2016,"componentId":0},{"id":"robert-doornbos","givenName":"Robert","familyName":"Doornbos","name":"Robert Michael Doornbos","activeFrom":2005,"activeTo":2006,"componentId":0},{"id":"robert-kubica","givenName":"Robert","familyName":"Kubica","name":"Robert Józef Kubica","activeFrom":2006,"activeTo":2021,"componentId":0},{"id":"roberto-merhi","givenName":"Roberto","familyName":"Merhi","name":"Roberto Merhi Muntan","activeFrom":2015,"activeTo":2015,"componentId":0},{"id":"romain-grosjean","givenName":"Romain","familyName":"Grosjean","name":"Romain David Jeremie Grosjean","activeFrom":2009,"activeTo":2020,"componentId":0},{"id":"rubens-barrichello","givenName":"Rubens","familyName":"Barrichello","name":"Rubens Gonçalves Barrichello","activeFrom":2000,"activeTo":2011,"componentId":0},{"id":"sakon-yamamoto","givenName":"Sakon","familyName":"Yamamoto","name":"Sakon Yamamoto","activeFrom":2006,"activeTo":2010,"componentId":0},{"id":"scott-speed","givenName":"Scott","familyName":"Speed","name":"Scott Andrew Speed","activeFrom":2006,"activeTo":2007,"componentId":0},{"id":"sebastian-vettel","givenName":"Sebastian","familyName":"Vettel","name":"Sebastian Vettel","activeFrom":2007,"activeTo":2022,"componentId":0},{"id":"sebastien-bourdais","givenName":"Sébastien","familyName":"Bourdais","name":"Sébastien Olivier Bourdais","activeFrom":2008,"activeTo":2009,"componentId":0},{"id":"sebastien-buemi","givenName":"Sébastien","familyName":"Buemi","name":"Sébastien Olivier Humbert Buemi","activeFrom":2009,"activeTo":2011,"componentId":0},{"id":"sergey-sirotkin","givenName":"Sergey","familyName":"Sirotkin","name":"Sergey Olegovich Sirotkin","activeFrom":2018,"activeTo":2018,"componentId":0},{"id":"sergio-perez","givenName":"Sergio","familyName":"Pérez","name":"Sergio Michel Pérez Mendoza","activeFrom":2011,"activeTo":2026,"componentId":0},{"id":"stoffel-vandoorne","givenName":"Stoffel","familyName":"Vandoorne","name":"Stoffel Jacques Luc Vandoorne","activeFrom":2016,"activeTo":2018,"componentId":0},{"id":"takuma-sato","givenName":"Takuma","familyName":"Sato","name":"Takuma Sato","activeFrom":2002,"activeTo":2008,"componentId":0},{"id":"tarso-marques","givenName":"Tarso","familyName":"Marques","name":"Tarso Anibal Santanna Marques","activeFrom":2001,"activeTo":2001,"componentId":0},{"id":"tiago-monteiro","givenName":"Tiago","familyName":"Monteiro","name":"Tiago Vagaroso da Costa Monteiro","activeFrom":2005,"activeTo":2006,"componentId":0},{"id":"timo-glock","givenName":"Timo","familyName":"Glock","name":"Timo Glock","activeFrom":2004,"activeTo":2012,"componentId":0},{"id":"tomas-enge","givenName":"Tomáš","familyName":"Enge","name":"Tomáš Enge","activeFrom":2001,"activeTo":2001,"componentId":0},{"id":"valtteri-bottas","givenName":"Valtteri","familyName":"Bottas","name":"Valtteri Viktor Bottas","activeFrom":2013,"activeTo":2026,"componentId":0},{"id":"vitaly-petrov","givenName":"Vitaly","familyName":"Petrov","name":"Vitaly Aleksandrovich Petrov","activeFrom":2010,"activeTo":2012,"componentId":0},{"id":"vitantonio-liuzzi","givenName":"Vitantonio","familyName":"Liuzzi","name":"Vitantonio Liuzzi","activeFrom":2005,"activeTo":2011,"componentId":0},{"id":"will-stevens","givenName":"Will","familyName":"Stevens","name":"William Jonathan Richard Stevens","activeFrom":2014,"activeTo":2015,"componentId":0},{"id":"yuji-ide","givenName":"Yuji","familyName":"Ide","name":"Yuji Ide","activeFrom":2006,"activeTo":2006,"componentId":0},{"id":"yuki-tsunoda","givenName":"Yuki","familyName":"Tsunoda","name":"Yuki Tsunoda","activeFrom":2021,"activeTo":2025,"componentId":0},{"id":"zsolt-baumgartner","givenName":"Zsolt","familyName":"Baumgartner","name":"Zsolt Baumgartner","activeFrom":2003,"activeTo":2004,"componentId":0}],"constructors":[{"id":"alfa-romeo","name":"Alfa Romeo","fullName":"Alfa Romeo Racing"},{"id":"alphatauri","name":"AlphaTauri","fullName":"Scuderia AlphaTauri"},{"id":"alpine","name":"Alpine","fullName":"Alpine F1 Team"},{"id":"arrows","name":"Arrows","fullName":"Arrows Grand Prix International"},{"id":"aston-martin","name":"Aston Martin","fullName":"Aston Martin"},{"id":"audi","name":"Audi","fullName":"Audi"},{"id":"bar","name":"BAR","fullName":"British American Racing"},{"id":"benetton","name":"Benetton","fullName":"Benetton Formula"},{"id":"bmw-sauber","name":"BMW Sauber","fullName":"BMW Sauber F1 Team"},{"id":"brawn","name":"Brawn","fullName":"Brawn GP Formula One Team"},{"id":"cadillac","name":"Cadillac","fullName":"Cadillac"},{"id":"caterham","name":"Caterham","fullName":"Caterham F1 Team"},{"id":"ferrari","name":"Ferrari","fullName":"Scuderia Ferrari"},{"id":"force-india","name":"Force India","fullName":"Force India F1 Team"},{"id":"haas","name":"Haas","fullName":"Haas F1 Team"},{"id":"honda","name":"Honda","fullName":"Honda Racing F1 Team"},{"id":"hrt","name":"HRT","fullName":"Hispania Racing Team"},{"id":"jaguar","name":"Jaguar","fullName":"Jaguar Racing F1 Team"},{"id":"jordan","name":"Jordan","fullName":"Jordan Grand Prix"},{"id":"kick-sauber","name":"Kick Sauber","fullName":"Kick Sauber F1 Team"},{"id":"lotus-f1","name":"Lotus","fullName":"Lotus F1 Team"},{"id":"lotus-racing","name":"Lotus Racing","fullName":"Lotus Racing"},{"id":"manor","name":"Manor","fullName":"Manor Racing"},{"id":"marussia","name":"Marussia","fullName":"Marussia F1 Team"},{"id":"mclaren","name":"McLaren","fullName":"McLaren Racing"},{"id":"mercedes","name":"Mercedes","fullName":"Mercedes AMG F1"},{"id":"midland","name":"Midland","fullName":"Midland F1 Racing"},{"id":"minardi","name":"Minardi","fullName":"Minardi F1 Team"},{"id":"prost","name":"Prost","fullName":"Prost Grand Prix"},{"id":"racing-bulls","name":"Racing Bulls","fullName":"Racing Bulls"},{"id":"racing-point","name":"Racing Point","fullName":"Racing Point F1 Team"},{"id":"rb","name":"RB","fullName":"Racing Bulls"},{"id":"red-bull","name":"Red Bull","fullName":"Red Bull Racing"},{"id":"renault","name":"Renault","fullName":"Renault Sport Formula One Team"},{"id":"sauber","name":"Sauber","fullName":"Sauber F1 Team"},{"id":"spyker","name":"Spyker","fullName":"Spyker F1 Team"},{"id":"super-aguri","name":"Super Aguri","fullName":"Super Aguri F1 Team"},{"id":"toro-rosso","name":"Toro Rosso","fullName":"Scuderia Toro Rosso"},{"id":"toyota","name":"Toyota","fullName":"Toyota Racing"},{"id":"virgin","name":"Virgin","fullName":"Virgin Racing"},{"id":"williams","name":"Williams","fullName":"Williams Grand Prix Engineering"}],"edges":[{"driverAId":"adrian-sutil","driverBId":"christijan-albers","sharedEventCount":9,"teams":[{"id":"spyker","name":"Spyker","eventCount":9,"firstSeason":2007,"lastSeason":2007,"firstEventId":"2007-01","lastEventId":"2007-09"}]},{"driverAId":"adrian-sutil","driverBId":"esteban-gutierrez","sharedEventCount":19,"teams":[{"id":"sauber","name":"Sauber","eventCount":19,"firstSeason":2014,"lastSeason":2014,"firstEventId":"2014-01","lastEventId":"2014-19"}]},{"driverAId":"adrian-sutil","driverBId":"giancarlo-fisichella","sharedEventCount":30,"teams":[{"id":"force-india","name":"Force India","eventCount":30,"firstSeason":2008,"lastSeason":2009,"firstEventId":"2008-01","lastEventId":"2009-12"}]},{"driverAId":"adrian-sutil","driverBId":"markus-winkelhock","sharedEventCount":1,"teams":[{"id":"spyker","name":"Spyker","eventCount":1,"firstSeason":2007,"lastSeason":2007,"firstEventId":"2007-10","lastEventId":"2007-10"}]},{"driverAId":"adrian-sutil","driverBId":"paul-di-resta","sharedEventCount":38,"teams":[{"id":"force-india","name":"Force India","eventCount":38,"firstSeason":2011,"lastSeason":2013,"firstEventId":"2011-01","lastEventId":"2013-19"}]},{"driverAId":"adrian-sutil","driverBId":"sakon-yamamoto","sharedEventCount":7,"teams":[{"id":"spyker","name":"Spyker","eventCount":7,"firstSeason":2007,"lastSeason":2007,"firstEventId":"2007-11","lastEventId":"2007-17"}]},{"driverAId":"adrian-sutil","driverBId":"vitantonio-liuzzi","sharedEventCount":24,"teams":[{"id":"force-india","name":"Force India","eventCount":24,"firstSeason":2009,"lastSeason":2010,"firstEventId":"2009-13","lastEventId":"2010-19"}]},{"driverAId":"alex-yoong","driverBId":"fernando-alonso","sharedEventCount":3,"teams":[{"id":"minardi","name":"Minardi","eventCount":3,"firstSeason":2001,"lastSeason":2001,"firstEventId":"2001-15","lastEventId":"2001-17"}]},{"driverAId":"alex-yoong","driverBId":"mark-webber","sharedEventCount":15,"teams":[{"id":"minardi","name":"Minardi","eventCount":15,"firstSeason":2002,"lastSeason":2002,"firstEventId":"2002-01","lastEventId":"2002-17"}]},{"driverAId":"alexander-albon","driverBId":"carlos-sainz-jr","sharedEventCount":34,"teams":[{"id":"williams","name":"Williams","eventCount":34,"firstSeason":2025,"lastSeason":2026,"firstEventId":"2025-01","lastEventId":"2026-10"}]},{"driverAId":"alexander-albon","driverBId":"daniil-kvyat","sharedEventCount":12,"teams":[{"id":"toro-rosso","name":"Toro Rosso","eventCount":12,"firstSeason":2019,"lastSeason":2019,"firstEventId":"2019-01","lastEventId":"2019-12"}]},{"driverAId":"alexander-albon","driverBId":"franco-colapinto","sharedEventCount":9,"teams":[{"id":"williams","name":"Williams","eventCount":9,"firstSeason":2024,"lastSeason":2024,"firstEventId":"2024-16","lastEventId":"2024-24"}]},{"driverAId":"alexander-albon","driverBId":"logan-sargeant","sharedEventCount":36,"teams":[{"id":"williams","name":"Williams","eventCount":36,"firstSeason":2023,"lastSeason":2024,"firstEventId":"2023-01","lastEventId":"2024-15"}]},{"driverAId":"alexander-albon","driverBId":"max-verstappen","sharedEventCount":26,"teams":[{"id":"red-bull","name":"Red Bull","eventCount":26,"firstSeason":2019,"lastSeason":2020,"firstEventId":"2019-13","lastEventId":"2020-17"}]},{"driverAId":"alexander-albon","driverBId":"nicholas-latifi","sharedEventCount":21,"teams":[{"id":"williams","name":"Williams","eventCount":21,"firstSeason":2022,"lastSeason":2022,"firstEventId":"2022-01","lastEventId":"2022-22"}]},{"driverAId":"alexander-rossi","driverBId":"will-stevens","sharedEventCount":5,"teams":[{"id":"marussia","name":"Marussia","eventCount":5,"firstSeason":2015,"lastSeason":2015,"firstEventId":"2015-13","lastEventId":"2015-18"}]},{"driverAId":"alexander-wurz","driverBId":"giancarlo-fisichella","sharedEventCount":17,"teams":[{"id":"benetton","name":"Benetton","eventCount":17,"firstSeason":2000,"lastSeason":2000,"firstEventId":"2000-01","lastEventId":"2000-17"}]},{"driverAId":"alexander-wurz","driverBId":"kimi-raikkonen","sharedEventCount":1,"teams":[{"id":"mclaren","name":"McLaren","eventCount":1,"firstSeason":2005,"lastSeason":2005,"firstEventId":"2005-04","lastEventId":"2005-04"}]},{"driverAId":"alexander-wurz","driverBId":"nico-rosberg","sharedEventCount":16,"teams":[{"id":"williams","name":"Williams","eventCount":16,"firstSeason":2007,"lastSeason":2007,"firstEventId":"2007-01","lastEventId":"2007-16"}]},{"driverAId":"allan-mcnish","driverBId":"mika-salo","sharedEventCount":17,"teams":[{"id":"toyota","name":"Toyota","eventCount":17,"firstSeason":2002,"lastSeason":2002,"firstEventId":"2002-01","lastEventId":"2002-17"}]},{"driverAId":"andre-lotterer","driverBId":"marcus-ericsson","sharedEventCount":1,"teams":[{"id":"caterham","name":"Caterham","eventCount":1,"firstSeason":2014,"lastSeason":2014,"firstEventId":"2014-12","lastEventId":"2014-12"}]},{"driverAId":"anthony-davidson","driverBId":"jenson-button","sharedEventCount":1,"teams":[{"id":"bar","name":"BAR","eventCount":1,"firstSeason":2005,"lastSeason":2005,"firstEventId":"2005-02","lastEventId":"2005-02"}]},{"driverAId":"anthony-davidson","driverBId":"mark-webber","sharedEventCount":2,"teams":[{"id":"minardi","name":"Minardi","eventCount":2,"firstSeason":2002,"lastSeason":2002,"firstEventId":"2002-13","lastEventId":"2002-14"}]},{"driverAId":"anthony-davidson","driverBId":"takuma-sato","sharedEventCount":21,"teams":[{"id":"super-aguri","name":"Super Aguri","eventCount":21,"firstSeason":2007,"lastSeason":2008,"firstEventId":"2007-01","lastEventId":"2008-04"}]},{"driverAId":"antonio-giovinazzi","driverBId":"kimi-raikkonen","sharedEventCount":58,"teams":[{"id":"alfa-romeo","name":"Alfa Romeo","eventCount":58,"firstSeason":2019,"lastSeason":2021,"firstEventId":"2019-01","lastEventId":"2021-22"}]},{"driverAId":"antonio-giovinazzi","driverBId":"marcus-ericsson","sharedEventCount":2,"teams":[{"id":"sauber","name":"Sauber","eventCount":2,"firstSeason":2017,"lastSeason":2017,"firstEventId":"2017-01","lastEventId":"2017-02"}]},{"driverAId":"antonio-giovinazzi","driverBId":"robert-kubica","sharedEventCount":2,"teams":[{"id":"alfa-romeo","name":"Alfa Romeo","eventCount":2,"firstSeason":2021,"lastSeason":2021,"firstEventId":"2021-13","lastEventId":"2021-14"}]},{"driverAId":"antonio-pizzonia","driverBId":"juan-pablo-montoya","sharedEventCount":4,"teams":[{"id":"williams","name":"Williams","eventCount":4,"firstSeason":2004,"lastSeason":2004,"firstEventId":"2004-12","lastEventId":"2004-15"}]},{"driverAId":"antonio-pizzonia","driverBId":"mark-webber","sharedEventCount":16,"teams":[{"id":"jaguar","name":"Jaguar","eventCount":11,"firstSeason":2003,"lastSeason":2003,"firstEventId":"2003-01","lastEventId":"2003-11"},{"id":"williams","name":"Williams","eventCount":5,"firstSeason":2005,"lastSeason":2005,"firstEventId":"2005-15","lastEventId":"2005-19"}]},{"driverAId":"arvid-lindblad","driverBId":"liam-lawson","sharedEventCount":10,"teams":[{"id":"racing-bulls","name":"Racing Bulls","eventCount":10,"firstSeason":2026,"lastSeason":2026,"firstEventId":"2026-01","lastEventId":"2026-10"}]},{"driverAId":"brendon-hartley","driverBId":"daniil-kvyat","sharedEventCount":1,"teams":[{"id":"toro-rosso","name":"Toro Rosso","eventCount":1,"firstSeason":2017,"lastSeason":2017,"firstEventId":"2017-17","lastEventId":"2017-17"}]},{"driverAId":"brendon-hartley","driverBId":"pierre-gasly","sharedEventCount":24,"teams":[{"id":"toro-rosso","name":"Toro Rosso","eventCount":24,"firstSeason":2017,"lastSeason":2018,"firstEventId":"2017-18","lastEventId":"2018-21"}]},{"driverAId":"bruno-senna","driverBId":"christian-klien","sharedEventCount":3,"teams":[{"id":"hrt","name":"HRT","eventCount":3,"firstSeason":2010,"lastSeason":2010,"firstEventId":"2010-15","lastEventId":"2010-19"}]},{"driverAId":"bruno-senna","driverBId":"karun-chandhok","sharedEventCount":9,"teams":[{"id":"hrt","name":"HRT","eventCount":9,"firstSeason":2010,"lastSeason":2010,"firstEventId":"2010-01","lastEventId":"2010-09"}]},{"driverAId":"bruno-senna","driverBId":"pastor-maldonado","sharedEventCount":20,"teams":[{"id":"williams","name":"Williams","eventCount":20,"firstSeason":2012,"lastSeason":2012,"firstEventId":"2012-01","lastEventId":"2012-20"}]},{"driverAId":"bruno-senna","driverBId":"sakon-yamamoto","sharedEventCount":6,"teams":[{"id":"hrt","name":"HRT","eventCount":6,"firstSeason":2010,"lastSeason":2010,"firstEventId":"2010-11","lastEventId":"2010-17"}]},{"driverAId":"bruno-senna","driverBId":"vitaly-petrov","sharedEventCount":8,"teams":[{"id":"renault","name":"Renault","eventCount":8,"firstSeason":2011,"lastSeason":2011,"firstEventId":"2011-12","lastEventId":"2011-19"}]},{"driverAId":"carlos-sainz-jr","driverBId":"charles-leclerc","sharedEventCount":89,"teams":[{"id":"ferrari","name":"Ferrari","eventCount":89,"firstSeason":2021,"lastSeason":2024,"firstEventId":"2021-01","lastEventId":"2024-24"}]},{"driverAId":"carlos-sainz-jr","driverBId":"daniil-kvyat","sharedEventCount":31,"teams":[{"id":"toro-rosso","name":"Toro Rosso","eventCount":31,"firstSeason":2016,"lastSeason":2017,"firstEventId":"2016-05","lastEventId":"2017-14"}]},{"driverAId":"carlos-sainz-jr","driverBId":"lando-norris","sharedEventCount":38,"teams":[{"id":"mclaren","name":"McLaren","eventCount":38,"firstSeason":2019,"lastSeason":2020,"firstEventId":"2019-01","lastEventId":"2020-17"}]},{"driverAId":"carlos-sainz-jr","driverBId":"max-verstappen","sharedEventCount":23,"teams":[{"id":"toro-rosso","name":"Toro Rosso","eventCount":23,"firstSeason":2015,"lastSeason":2016,"firstEventId":"2015-01","lastEventId":"2016-04"}]},{"driverAId":"carlos-sainz-jr","driverBId":"nico-hulkenberg","sharedEventCount":25,"teams":[{"id":"renault","name":"Renault","eventCount":25,"firstSeason":2017,"lastSeason":2018,"firstEventId":"2017-17","lastEventId":"2018-21"}]},{"driverAId":"carlos-sainz-jr","driverBId":"pierre-gasly","sharedEventCount":2,"teams":[{"id":"toro-rosso","name":"Toro Rosso","eventCount":2,"firstSeason":2017,"lastSeason":2017,"firstEventId":"2017-15","lastEventId":"2017-16"}]},{"driverAId":"charles-leclerc","driverBId":"lewis-hamilton","sharedEventCount":34,"teams":[{"id":"ferrari","name":"Ferrari","eventCount":34,"firstSeason":2025,"lastSeason":2026,"firstEventId":"2025-01","lastEventId":"2026-10"}]},{"driverAId":"charles-leclerc","driverBId":"marcus-ericsson","sharedEventCount":21,"teams":[{"id":"sauber","name":"Sauber","eventCount":21,"firstSeason":2018,"lastSeason":2018,"firstEventId":"2018-01","lastEventId":"2018-21"}]},{"driverAId":"charles-leclerc","driverBId":"oliver-bearman","sharedEventCount":1,"teams":[{"id":"ferrari","name":"Ferrari","eventCount":1,"firstSeason":2024,"lastSeason":2024,"firstEventId":"2024-02","lastEventId":"2024-02"}]},{"driverAId":"charles-leclerc","driverBId":"sebastian-vettel","sharedEventCount":38,"teams":[{"id":"ferrari","name":"Ferrari","eventCount":38,"firstSeason":2019,"lastSeason":2020,"firstEventId":"2019-01","lastEventId":"2020-17"}]},{"driverAId":"charles-pic","driverBId":"giedo-van-der-garde","sharedEventCount":19,"teams":[{"id":"caterham","name":"Caterham","eventCount":19,"firstSeason":2013,"lastSeason":2013,"firstEventId":"2013-01","lastEventId":"2013-19"}]},{"driverAId":"charles-pic","driverBId":"timo-glock","sharedEventCount":20,"teams":[{"id":"marussia","name":"Marussia","eventCount":20,"firstSeason":2012,"lastSeason":2012,"firstEventId":"2012-01","lastEventId":"2012-20"}]},{"driverAId":"christian-klien","driverBId":"david-coulthard","sharedEventCount":30,"teams":[{"id":"red-bull","name":"Red Bull","eventCount":30,"firstSeason":2005,"lastSeason":2006,"firstEventId":"2005-01","lastEventId":"2006-15"}]},{"driverAId":"christian-klien","driverBId":"mark-webber","sharedEventCount":18,"teams":[{"id":"jaguar","name":"Jaguar","eventCount":18,"firstSeason":2004,"lastSeason":2004,"firstEventId":"2004-01","lastEventId":"2004-18"}]},{"driverAId":"christijan-albers","driverBId":"patrick-friesacher","sharedEventCount":11,"teams":[{"id":"minardi","name":"Minardi","eventCount":11,"firstSeason":2005,"lastSeason":2005,"firstEventId":"2005-01","lastEventId":"2005-11"}]},{"driverAId":"christijan-albers","driverBId":"robert-doornbos","sharedEventCount":8,"teams":[{"id":"minardi","name":"Minardi","eventCount":8,"firstSeason":2005,"lastSeason":2005,"firstEventId":"2005-12","lastEventId":"2005-19"}]},{"driverAId":"christijan-albers","driverBId":"tiago-monteiro","sharedEventCount":18,"teams":[{"id":"midland","name":"Midland","eventCount":18,"firstSeason":2006,"lastSeason":2006,"firstEventId":"2006-01","lastEventId":"2006-18"}]},{"driverAId":"cristiano-da-matta","driverBId":"olivier-panis","sharedEventCount":28,"teams":[{"id":"toyota","name":"Toyota","eventCount":28,"firstSeason":2003,"lastSeason":2004,"firstEventId":"2003-01","lastEventId":"2004-12"}]},{"driverAId":"daniel-ricciardo","driverBId":"daniil-kvyat","sharedEventCount":23,"teams":[{"id":"red-bull","name":"Red Bull","eventCount":23,"firstSeason":2015,"lastSeason":2016,"firstEventId":"2015-01","lastEventId":"2016-04"}]},{"driverAId":"daniel-ricciardo","driverBId":"esteban-ocon","sharedEventCount":17,"teams":[{"id":"renault","name":"Renault","eventCount":17,"firstSeason":2020,"lastSeason":2020,"firstEventId":"2020-01","lastEventId":"2020-17"}]},{"driverAId":"daniel-ricciardo","driverBId":"jean-eric-vergne","sharedEventCount":39,"teams":[{"id":"toro-rosso","name":"Toro Rosso","eventCount":39,"firstSeason":2012,"lastSeason":2013,"firstEventId":"2012-01","lastEventId":"2013-19"}]},{"driverAId":"daniel-ricciardo","driverBId":"lando-norris","sharedEventCount":44,"teams":[{"id":"mclaren","name":"McLaren","eventCount":44,"firstSeason":2021,"lastSeason":2022,"firstEventId":"2021-01","lastEventId":"2022-22"}]},{"driverAId":"daniel-ricciardo","driverBId":"max-verstappen","sharedEventCount":58,"teams":[{"id":"red-bull","name":"Red Bull","eventCount":58,"firstSeason":2016,"lastSeason":2018,"firstEventId":"2016-05","lastEventId":"2018-21"}]},{"driverAId":"daniel-ricciardo","driverBId":"narain-karthikeyan","sharedEventCount":1,"teams":[{"id":"hrt","name":"HRT","eventCount":1,"firstSeason":2011,"lastSeason":2011,"firstEventId":"2011-17","lastEventId":"2011-17"}]},{"driverAId":"daniel-ricciardo","driverBId":"nico-hulkenberg","sharedEventCount":21,"teams":[{"id":"renault","name":"Renault","eventCount":21,"firstSeason":2019,"lastSeason":2019,"firstEventId":"2019-01","lastEventId":"2019-21"}]},{"driverAId":"daniel-ricciardo","driverBId":"sebastian-vettel","sharedEventCount":19,"teams":[{"id":"red-bull","name":"Red Bull","eventCount":19,"firstSeason":2014,"lastSeason":2014,"firstEventId":"2014-01","lastEventId":"2014-19"}]},{"driverAId":"daniel-ricciardo","driverBId":"vitantonio-liuzzi","sharedEventCount":10,"teams":[{"id":"hrt","name":"HRT","eventCount":10,"firstSeason":2011,"lastSeason":2011,"firstEventId":"2011-09","lastEventId":"2011-19"}]},{"driverAId":"daniel-ricciardo","driverBId":"yuki-tsunoda","sharedEventCount":25,"teams":[{"id":"alphatauri","name":"AlphaTauri","eventCount":7,"firstSeason":2023,"lastSeason":2023,"firstEventId":"2023-11","lastEventId":"2023-22"},{"id":"rb","name":"RB","eventCount":18,"firstSeason":2024,"lastSeason":2024,"firstEventId":"2024-01","lastEventId":"2024-18"}]},{"driverAId":"daniil-kvyat","driverBId":"jean-eric-vergne","sharedEventCount":19,"teams":[{"id":"toro-rosso","name":"Toro Rosso","eventCount":19,"firstSeason":2014,"lastSeason":2014,"firstEventId":"2014-01","lastEventId":"2014-19"}]},{"driverAId":"daniil-kvyat","driverBId":"pierre-gasly","sharedEventCount":26,"teams":[{"id":"alphatauri","name":"AlphaTauri","eventCount":17,"firstSeason":2020,"lastSeason":2020,"firstEventId":"2020-01","lastEventId":"2020-17"},{"id":"toro-rosso","name":"Toro Rosso","eventCount":9,"firstSeason":2019,"lastSeason":2019,"firstEventId":"2019-13","lastEventId":"2019-21"}]},{"driverAId":"david-coulthard","driverBId":"kimi-raikkonen","sharedEventCount":51,"teams":[{"id":"mclaren","name":"McLaren","eventCount":51,"firstSeason":2002,"lastSeason":2004,"firstEventId":"2002-01","lastEventId":"2004-18"}]},{"driverAId":"david-coulthard","driverBId":"mark-webber","sharedEventCount":35,"teams":[{"id":"red-bull","name":"Red Bull","eventCount":35,"firstSeason":2007,"lastSeason":2008,"firstEventId":"2007-01","lastEventId":"2008-18"}]},{"driverAId":"david-coulthard","driverBId":"mika-hakkinen","sharedEventCount":34,"teams":[{"id":"mclaren","name":"McLaren","eventCount":34,"firstSeason":2000,"lastSeason":2001,"firstEventId":"2000-01","lastEventId":"2001-17"}]},{"driverAId":"david-coulthard","driverBId":"robert-doornbos","sharedEventCount":3,"teams":[{"id":"red-bull","name":"Red Bull","eventCount":3,"firstSeason":2006,"lastSeason":2006,"firstEventId":"2006-16","lastEventId":"2006-18"}]},{"driverAId":"david-coulthard","driverBId":"vitantonio-liuzzi","sharedEventCount":4,"teams":[{"id":"red-bull","name":"Red Bull","eventCount":4,"firstSeason":2005,"lastSeason":2005,"firstEventId":"2005-04","lastEventId":"2005-07"}]},{"driverAId":"eddie-irvine","driverBId":"johnny-herbert","sharedEventCount":16,"teams":[{"id":"jaguar","name":"Jaguar","eventCount":16,"firstSeason":2000,"lastSeason":2000,"firstEventId":"2000-01","lastEventId":"2000-17"}]},{"driverAId":"eddie-irvine","driverBId":"luciano-burti","sharedEventCount":4,"teams":[{"id":"jaguar","name":"Jaguar","eventCount":4,"firstSeason":2001,"lastSeason":2001,"firstEventId":"2001-01","lastEventId":"2001-04"}]},{"driverAId":"eddie-irvine","driverBId":"pedro-de-la-rosa","sharedEventCount":30,"teams":[{"id":"jaguar","name":"Jaguar","eventCount":30,"firstSeason":2001,"lastSeason":2002,"firstEventId":"2001-05","lastEventId":"2002-17"}]},{"driverAId":"enrique-bernoldi","driverBId":"heinz-harald-frentzen","sharedEventCount":12,"teams":[{"id":"arrows","name":"Arrows","eventCount":12,"firstSeason":2002,"lastSeason":2002,"firstEventId":"2002-01","lastEventId":"2002-12"}]},{"driverAId":"enrique-bernoldi","driverBId":"jos-verstappen","sharedEventCount":17,"teams":[{"id":"arrows","name":"Arrows","eventCount":17,"firstSeason":2001,"lastSeason":2001,"firstEventId":"2001-01","lastEventId":"2001-17"}]},{"driverAId":"esteban-gutierrez","driverBId":"nico-hulkenberg","sharedEventCount":19,"teams":[{"id":"sauber","name":"Sauber","eventCount":19,"firstSeason":2013,"lastSeason":2013,"firstEventId":"2013-01","lastEventId":"2013-19"}]},{"driverAId":"esteban-gutierrez","driverBId":"romain-grosjean","sharedEventCount":21,"teams":[{"id":"haas","name":"Haas","eventCount":21,"firstSeason":2016,"lastSeason":2016,"firstEventId":"2016-01","lastEventId":"2016-21"}]},{"driverAId":"esteban-ocon","driverBId":"fernando-alonso","sharedEventCount":44,"teams":[{"id":"alpine","name":"Alpine","eventCount":44,"firstSeason":2021,"lastSeason":2022,"firstEventId":"2021-01","lastEventId":"2022-22"}]},{"driverAId":"esteban-ocon","driverBId":"oliver-bearman","sharedEventCount":34,"teams":[{"id":"haas","name":"Haas","eventCount":34,"firstSeason":2025,"lastSeason":2026,"firstEventId":"2025-01","lastEventId":"2026-10"}]},{"driverAId":"esteban-ocon","driverBId":"pascal-wehrlein","sharedEventCount":9,"teams":[{"id":"manor","name":"Manor","eventCount":9,"firstSeason":2016,"lastSeason":2016,"firstEventId":"2016-13","lastEventId":"2016-21"}]},{"driverAId":"esteban-ocon","driverBId":"pierre-gasly","sharedEventCount":45,"teams":[{"id":"alpine","name":"Alpine","eventCount":45,"firstSeason":2023,"lastSeason":2024,"firstEventId":"2023-01","lastEventId":"2024-23"}]},{"driverAId":"esteban-ocon","driverBId":"sergio-perez","sharedEventCount":41,"teams":[{"id":"force-india","name":"Force India","eventCount":41,"firstSeason":2017,"lastSeason":2018,"firstEventId":"2017-01","lastEventId":"2018-21"}]},{"driverAId":"felipe-massa","driverBId":"fernando-alonso","sharedEventCount":77,"teams":[{"id":"ferrari","name":"Ferrari","eventCount":77,"firstSeason":2010,"lastSeason":2013,"firstEventId":"2010-01","lastEventId":"2013-19"}]},{"driverAId":"felipe-massa","driverBId":"giancarlo-fisichella","sharedEventCount":18,"teams":[{"id":"sauber","name":"Sauber","eventCount":18,"firstSeason":2004,"lastSeason":2004,"firstEventId":"2004-01","lastEventId":"2004-18"}]},{"driverAId":"felipe-massa","driverBId":"jacques-villeneuve","sharedEventCount":19,"teams":[{"id":"sauber","name":"Sauber","eventCount":19,"firstSeason":2005,"lastSeason":2005,"firstEventId":"2005-01","lastEventId":"2005-19"}]},{"driverAId":"felipe-massa","driverBId":"kimi-raikkonen","sharedEventCount":45,"teams":[{"id":"ferrari","name":"Ferrari","eventCount":45,"firstSeason":2007,"lastSeason":2009,"firstEventId":"2007-01","lastEventId":"2009-10"}]},{"driverAId":"felipe-massa","driverBId":"lance-stroll","sharedEventCount":19,"teams":[{"id":"williams","name":"Williams","eventCount":19,"firstSeason":2017,"lastSeason":2017,"firstEventId":"2017-01","lastEventId":"2017-20"}]},{"driverAId":"felipe-massa","driverBId":"michael-schumacher","sharedEventCount":18,"teams":[{"id":"ferrari","name":"Ferrari","eventCount":18,"firstSeason":2006,"lastSeason":2006,"firstEventId":"2006-01","lastEventId":"2006-18"}]},{"driverAId":"felipe-massa","driverBId":"nick-heidfeld","sharedEventCount":16,"teams":[{"id":"sauber","name":"Sauber","eventCount":16,"firstSeason":2002,"lastSeason":2002,"firstEventId":"2002-01","lastEventId":"2002-17"}]},{"driverAId":"felipe-massa","driverBId":"valtteri-bottas","sharedEventCount":59,"teams":[{"id":"williams","name":"Williams","eventCount":59,"firstSeason":2014,"lastSeason":2016,"firstEventId":"2014-01","lastEventId":"2016-21"}]},{"driverAId":"felipe-nasr","driverBId":"marcus-ericsson","sharedEventCount":40,"teams":[{"id":"sauber","name":"Sauber","eventCount":40,"firstSeason":2015,"lastSeason":2016,"firstEventId":"2015-01","lastEventId":"2016-21"}]},{"driverAId":"fernando-alonso","driverBId":"giancarlo-fisichella","sharedEventCount":37,"teams":[{"id":"renault","name":"Renault","eventCount":37,"firstSeason":2005,"lastSeason":2006,"firstEventId":"2005-01","lastEventId":"2006-18"}]},{"driverAId":"fernando-alonso","driverBId":"jacques-villeneuve","sharedEventCount":3,"teams":[{"id":"renault","name":"Renault","eventCount":3,"firstSeason":2004,"lastSeason":2004,"firstEventId":"2004-16","lastEventId":"2004-18"}]},{"driverAId":"fernando-alonso","driverBId":"jarno-trulli","sharedEventCount":31,"teams":[{"id":"renault","name":"Renault","eventCount":31,"firstSeason":2003,"lastSeason":2004,"firstEventId":"2003-01","lastEventId":"2004-15"}]},{"driverAId":"fernando-alonso","driverBId":"jenson-button","sharedEventCount":38,"teams":[{"id":"mclaren","name":"McLaren","eventCount":38,"firstSeason":2015,"lastSeason":2016,"firstEventId":"2015-02","lastEventId":"2016-21"}]},{"driverAId":"fernando-alonso","driverBId":"kimi-raikkonen","sharedEventCount":19,"teams":[{"id":"ferrari","name":"Ferrari","eventCount":19,"firstSeason":2014,"lastSeason":2014,"firstEventId":"2014-01","lastEventId":"2014-19"}]},{"driverAId":"fernando-alonso","driverBId":"lance-stroll","sharedEventCount":80,"teams":[{"id":"aston-martin","name":"Aston Martin","eventCount":80,"firstSeason":2023,"lastSeason":2026,"firstEventId":"2023-01","lastEventId":"2026-10"}]},{"driverAId":"fernando-alonso","driverBId":"lewis-hamilton","sharedEventCount":17,"teams":[{"id":"mclaren","name":"McLaren","eventCount":17,"firstSeason":2007,"lastSeason":2007,"firstEventId":"2007-01","lastEventId":"2007-17"}]},{"driverAId":"fernando-alonso","driverBId":"nelson-piquet-jr","sharedEventCount":28,"teams":[{"id":"renault","name":"Renault","eventCount":28,"firstSeason":2008,"lastSeason":2009,"firstEventId":"2008-01","lastEventId":"2009-10"}]},{"driverAId":"fernando-alonso","driverBId":"romain-grosjean","sharedEventCount":7,"teams":[{"id":"renault","name":"Renault","eventCount":7,"firstSeason":2009,"lastSeason":2009,"firstEventId":"2009-11","lastEventId":"2009-17"}]},{"driverAId":"fernando-alonso","driverBId":"stoffel-vandoorne","sharedEventCount":40,"teams":[{"id":"mclaren","name":"McLaren","eventCount":40,"firstSeason":2017,"lastSeason":2018,"firstEventId":"2017-01","lastEventId":"2018-21"}]},{"driverAId":"fernando-alonso","driverBId":"tarso-marques","sharedEventCount":14,"teams":[{"id":"minardi","name":"Minardi","eventCount":14,"firstSeason":2001,"lastSeason":2001,"firstEventId":"2001-01","lastEventId":"2001-14"}]},{"driverAId":"franck-montagny","driverBId":"takuma-sato","sharedEventCount":7,"teams":[{"id":"super-aguri","name":"Super Aguri","eventCount":7,"firstSeason":2006,"lastSeason":2006,"firstEventId":"2006-05","lastEventId":"2006-11"}]},{"driverAId":"franco-colapinto","driverBId":"pierre-gasly","sharedEventCount":28,"teams":[{"id":"alpine","name":"Alpine","eventCount":28,"firstSeason":2025,"lastSeason":2026,"firstEventId":"2025-07","lastEventId":"2026-10"}]},{"driverAId":"gabriel-bortoleto","driverBId":"nico-hulkenberg","sharedEventCount":34,"teams":[{"id":"audi","name":"Audi","eventCount":10,"firstSeason":2026,"lastSeason":2026,"firstEventId":"2026-01","lastEventId":"2026-10"},{"id":"kick-sauber","name":"Kick Sauber","eventCount":24,"firstSeason":2025,"lastSeason":2025,"firstEventId":"2025-01","lastEventId":"2025-24"}]},{"driverAId":"gaston-mazzacane","driverBId":"jean-alesi","sharedEventCount":4,"teams":[{"id":"prost","name":"Prost","eventCount":4,"firstSeason":2001,"lastSeason":2001,"firstEventId":"2001-01","lastEventId":"2001-04"}]},{"driverAId":"gaston-mazzacane","driverBId":"marc-gene","sharedEventCount":17,"teams":[{"id":"minardi","name":"Minardi","eventCount":17,"firstSeason":2000,"lastSeason":2000,"firstEventId":"2000-01","lastEventId":"2000-17"}]},{"driverAId":"george-russell","driverBId":"kimi-antonelli","sharedEventCount":34,"teams":[{"id":"mercedes","name":"Mercedes","eventCount":34,"firstSeason":2025,"lastSeason":2026,"firstEventId":"2025-01","lastEventId":"2026-10"}]},{"driverAId":"george-russell","driverBId":"lewis-hamilton","sharedEventCount":68,"teams":[{"id":"mercedes","name":"Mercedes","eventCount":68,"firstSeason":2022,"lastSeason":2024,"firstEventId":"2022-01","lastEventId":"2024-24"}]},{"driverAId":"george-russell","driverBId":"nicholas-latifi","sharedEventCount":38,"teams":[{"id":"williams","name":"Williams","eventCount":38,"firstSeason":2020,"lastSeason":2021,"firstEventId":"2020-01","lastEventId":"2021-22"}]},{"driverAId":"george-russell","driverBId":"robert-kubica","sharedEventCount":21,"teams":[{"id":"williams","name":"Williams","eventCount":21,"firstSeason":2019,"lastSeason":2019,"firstEventId":"2019-01","lastEventId":"2019-21"}]},{"driverAId":"george-russell","driverBId":"valtteri-bottas","sharedEventCount":1,"teams":[{"id":"mercedes","name":"Mercedes","eventCount":1,"firstSeason":2020,"lastSeason":2020,"firstEventId":"2020-16","lastEventId":"2020-16"}]},{"driverAId":"giancarlo-fisichella","driverBId":"heikki-kovalainen","sharedEventCount":17,"teams":[{"id":"renault","name":"Renault","eventCount":17,"firstSeason":2007,"lastSeason":2007,"firstEventId":"2007-01","lastEventId":"2007-17"}]},{"driverAId":"giancarlo-fisichella","driverBId":"jenson-button","sharedEventCount":17,"teams":[{"id":"benetton","name":"Benetton","eventCount":17,"firstSeason":2001,"lastSeason":2001,"firstEventId":"2001-01","lastEventId":"2001-17"}]},{"driverAId":"giancarlo-fisichella","driverBId":"kimi-raikkonen","sharedEventCount":5,"teams":[{"id":"ferrari","name":"Ferrari","eventCount":5,"firstSeason":2009,"lastSeason":2009,"firstEventId":"2009-13","lastEventId":"2009-17"}]},{"driverAId":"giancarlo-fisichella","driverBId":"ralph-firman","sharedEventCount":14,"teams":[{"id":"jordan","name":"Jordan","eventCount":14,"firstSeason":2003,"lastSeason":2003,"firstEventId":"2003-01","lastEventId":"2003-16"}]},{"driverAId":"giancarlo-fisichella","driverBId":"takuma-sato","sharedEventCount":17,"teams":[{"id":"jordan","name":"Jordan","eventCount":17,"firstSeason":2002,"lastSeason":2002,"firstEventId":"2002-01","lastEventId":"2002-17"}]},{"driverAId":"giancarlo-fisichella","driverBId":"zsolt-baumgartner","sharedEventCount":2,"teams":[{"id":"jordan","name":"Jordan","eventCount":2,"firstSeason":2003,"lastSeason":2003,"firstEventId":"2003-13","lastEventId":"2003-14"}]},{"driverAId":"gianmaria-bruni","driverBId":"zsolt-baumgartner","sharedEventCount":18,"teams":[{"id":"minardi","name":"Minardi","eventCount":18,"firstSeason":2004,"lastSeason":2004,"firstEventId":"2004-01","lastEventId":"2004-18"}]},{"driverAId":"giorgio-pantano","driverBId":"nick-heidfeld","sharedEventCount":14,"teams":[{"id":"jordan","name":"Jordan","eventCount":14,"firstSeason":2004,"lastSeason":2004,"firstEventId":"2004-01","lastEventId":"2004-15"}]},{"driverAId":"guanyu-zhou","driverBId":"valtteri-bottas","sharedEventCount":68,"teams":[{"id":"alfa-romeo","name":"Alfa Romeo","eventCount":44,"firstSeason":2022,"lastSeason":2023,"firstEventId":"2022-01","lastEventId":"2023-22"},{"id":"kick-sauber","name":"Kick Sauber","eventCount":24,"firstSeason":2024,"lastSeason":2024,"firstEventId":"2024-01","lastEventId":"2024-24"}]},{"driverAId":"heikki-kovalainen","driverBId":"jarno-trulli","sharedEventCount":37,"teams":[{"id":"lotus-racing","name":"Lotus Racing","eventCount":37,"firstSeason":2010,"lastSeason":2011,"firstEventId":"2010-01","lastEventId":"2011-19"}]},{"driverAId":"heikki-kovalainen","driverBId":"karun-chandhok","sharedEventCount":1,"teams":[{"id":"lotus-racing","name":"Lotus Racing","eventCount":1,"firstSeason":2011,"lastSeason":2011,"firstEventId":"2011-10","lastEventId":"2011-10"}]},{"driverAId":"heikki-kovalainen","driverBId":"lewis-hamilton","sharedEventCount":35,"teams":[{"id":"mclaren","name":"McLaren","eventCount":35,"firstSeason":2008,"lastSeason":2009,"firstEventId":"2008-01","lastEventId":"2009-17"}]},{"driverAId":"heikki-kovalainen","driverBId":"romain-grosjean","sharedEventCount":2,"teams":[{"id":"lotus-f1","name":"Lotus","eventCount":2,"firstSeason":2013,"lastSeason":2013,"firstEventId":"2013-18","lastEventId":"2013-19"}]},{"driverAId":"heikki-kovalainen","driverBId":"vitaly-petrov","sharedEventCount":20,"teams":[{"id":"caterham","name":"Caterham","eventCount":20,"firstSeason":2012,"lastSeason":2012,"firstEventId":"2012-01","lastEventId":"2012-20"}]},{"driverAId":"heinz-harald-frentzen","driverBId":"jarno-trulli","sharedEventCount":27,"teams":[{"id":"jordan","name":"Jordan","eventCount":27,"firstSeason":2000,"lastSeason":2001,"firstEventId":"2000-01","lastEventId":"2001-11"}]},{"driverAId":"heinz-harald-frentzen","driverBId":"luciano-burti","sharedEventCount":2,"teams":[{"id":"prost","name":"Prost","eventCount":2,"firstSeason":2001,"lastSeason":2001,"firstEventId":"2001-13","lastEventId":"2001-14"}]},{"driverAId":"heinz-harald-frentzen","driverBId":"nick-heidfeld","sharedEventCount":17,"teams":[{"id":"sauber","name":"Sauber","eventCount":17,"firstSeason":2002,"lastSeason":2003,"firstEventId":"2002-16","lastEventId":"2003-16"}]},{"driverAId":"heinz-harald-frentzen","driverBId":"tomas-enge","sharedEventCount":3,"teams":[{"id":"prost","name":"Prost","eventCount":3,"firstSeason":2001,"lastSeason":2001,"firstEventId":"2001-15","lastEventId":"2001-17"}]},{"driverAId":"isack-hadjar","driverBId":"liam-lawson","sharedEventCount":22,"teams":[{"id":"racing-bulls","name":"Racing Bulls","eventCount":22,"firstSeason":2025,"lastSeason":2025,"firstEventId":"2025-03","lastEventId":"2025-24"}]},{"driverAId":"isack-hadjar","driverBId":"max-verstappen","sharedEventCount":10,"teams":[{"id":"red-bull","name":"Red Bull","eventCount":10,"firstSeason":2026,"lastSeason":2026,"firstEventId":"2026-01","lastEventId":"2026-10"}]},{"driverAId":"isack-hadjar","driverBId":"yuki-tsunoda","sharedEventCount":2,"teams":[{"id":"racing-bulls","name":"Racing Bulls","eventCount":2,"firstSeason":2025,"lastSeason":2025,"firstEventId":"2025-01","lastEventId":"2025-02"}]},{"driverAId":"jack-aitken","driverBId":"nicholas-latifi","sharedEventCount":1,"teams":[{"id":"williams","name":"Williams","eventCount":1,"firstSeason":2020,"lastSeason":2020,"firstEventId":"2020-16","lastEventId":"2020-16"}]},{"driverAId":"jack-doohan","driverBId":"pierre-gasly","sharedEventCount":7,"teams":[{"id":"alpine","name":"Alpine","eventCount":7,"firstSeason":2024,"lastSeason":2025,"firstEventId":"2024-24","lastEventId":"2025-06"}]},{"driverAId":"jacques-villeneuve","driverBId":"jenson-button","sharedEventCount":15,"teams":[{"id":"bar","name":"BAR","eventCount":15,"firstSeason":2003,"lastSeason":2003,"firstEventId":"2003-01","lastEventId":"2003-15"}]},{"driverAId":"jacques-villeneuve","driverBId":"nick-heidfeld","sharedEventCount":12,"teams":[{"id":"bmw-sauber","name":"BMW Sauber","eventCount":12,"firstSeason":2006,"lastSeason":2006,"firstEventId":"2006-01","lastEventId":"2006-12"}]},{"driverAId":"jacques-villeneuve","driverBId":"olivier-panis","sharedEventCount":34,"teams":[{"id":"bar","name":"BAR","eventCount":34,"firstSeason":2001,"lastSeason":2002,"firstEventId":"2001-01","lastEventId":"2002-17"}]},{"driverAId":"jacques-villeneuve","driverBId":"ricardo-zonta","sharedEventCount":17,"teams":[{"id":"bar","name":"BAR","eventCount":17,"firstSeason":2000,"lastSeason":2000,"firstEventId":"2000-01","lastEventId":"2000-17"}]},{"driverAId":"jaime-alguersuari","driverBId":"sebastien-buemi","sharedEventCount":46,"teams":[{"id":"toro-rosso","name":"Toro Rosso","eventCount":46,"firstSeason":2009,"lastSeason":2011,"firstEventId":"2009-10","lastEventId":"2011-19"}]},{"driverAId":"jarno-trulli","driverBId":"jean-alesi","sharedEventCount":5,"teams":[{"id":"jordan","name":"Jordan","eventCount":5,"firstSeason":2001,"lastSeason":2001,"firstEventId":"2001-13","lastEventId":"2001-17"}]},{"driverAId":"jarno-trulli","driverBId":"jenson-button","sharedEventCount":17,"teams":[{"id":"renault","name":"Renault","eventCount":17,"firstSeason":2002,"lastSeason":2002,"firstEventId":"2002-01","lastEventId":"2002-17"}]},{"driverAId":"jarno-trulli","driverBId":"kamui-kobayashi","sharedEventCount":2,"teams":[{"id":"toyota","name":"Toyota","eventCount":2,"firstSeason":2009,"lastSeason":2009,"firstEventId":"2009-16","lastEventId":"2009-17"}]},{"driverAId":"jarno-trulli","driverBId":"olivier-panis","sharedEventCount":1,"teams":[{"id":"toyota","name":"Toyota","eventCount":1,"firstSeason":2004,"lastSeason":2004,"firstEventId":"2004-17","lastEventId":"2004-17"}]},{"driverAId":"jarno-trulli","driverBId":"ralf-schumacher","sharedEventCount":53,"teams":[{"id":"toyota","name":"Toyota","eventCount":53,"firstSeason":2005,"lastSeason":2007,"firstEventId":"2005-01","lastEventId":"2007-17"}]},{"driverAId":"jarno-trulli","driverBId":"ricardo-zonta","sharedEventCount":4,"teams":[{"id":"jordan","name":"Jordan","eventCount":2,"firstSeason":2001,"lastSeason":2001,"firstEventId":"2001-08","lastEventId":"2001-12"},{"id":"toyota","name":"Toyota","eventCount":2,"firstSeason":2004,"lastSeason":2005,"firstEventId":"2004-18","lastEventId":"2005-09"}]},{"driverAId":"jarno-trulli","driverBId":"timo-glock","sharedEventCount":33,"teams":[{"id":"toyota","name":"Toyota","eventCount":33,"firstSeason":2008,"lastSeason":2009,"firstEventId":"2008-01","lastEventId":"2009-15"}]},{"driverAId":"jean-alesi","driverBId":"luciano-burti","sharedEventCount":8,"teams":[{"id":"prost","name":"Prost","eventCount":8,"firstSeason":2001,"lastSeason":2001,"firstEventId":"2001-05","lastEventId":"2001-12"}]},{"driverAId":"jean-alesi","driverBId":"nick-heidfeld","sharedEventCount":17,"teams":[{"id":"prost","name":"Prost","eventCount":17,"firstSeason":2000,"lastSeason":2000,"firstEventId":"2000-01","lastEventId":"2000-17"}]},{"driverAId":"jenson-button","driverBId":"kevin-magnussen","sharedEventCount":20,"teams":[{"id":"mclaren","name":"McLaren","eventCount":20,"firstSeason":2014,"lastSeason":2015,"firstEventId":"2014-01","lastEventId":"2015-01"}]},{"driverAId":"jenson-button","driverBId":"lewis-hamilton","sharedEventCount":58,"teams":[{"id":"mclaren","name":"McLaren","eventCount":58,"firstSeason":2010,"lastSeason":2012,"firstEventId":"2010-01","lastEventId":"2012-20"}]},{"driverAId":"jenson-button","driverBId":"ralf-schumacher","sharedEventCount":17,"teams":[{"id":"williams","name":"Williams","eventCount":17,"firstSeason":2000,"lastSeason":2000,"firstEventId":"2000-01","lastEventId":"2000-17"}]},{"driverAId":"jenson-button","driverBId":"rubens-barrichello","sharedEventCount":70,"teams":[{"id":"brawn","name":"Brawn","eventCount":17,"firstSeason":2009,"lastSeason":2009,"firstEventId":"2009-01","lastEventId":"2009-17"},{"id":"honda","name":"Honda","eventCount":53,"firstSeason":2006,"lastSeason":2008,"firstEventId":"2006-01","lastEventId":"2008-18"}]},{"driverAId":"jenson-button","driverBId":"sergio-perez","sharedEventCount":19,"teams":[{"id":"mclaren","name":"McLaren","eventCount":19,"firstSeason":2013,"lastSeason":2013,"firstEventId":"2013-01","lastEventId":"2013-19"}]},{"driverAId":"jenson-button","driverBId":"stoffel-vandoorne","sharedEventCount":2,"teams":[{"id":"mclaren","name":"McLaren","eventCount":2,"firstSeason":2016,"lastSeason":2017,"firstEventId":"2016-02","lastEventId":"2017-06"}]},{"driverAId":"jenson-button","driverBId":"takuma-sato","sharedEventCount":35,"teams":[{"id":"bar","name":"BAR","eventCount":35,"firstSeason":2003,"lastSeason":2005,"firstEventId":"2003-16","lastEventId":"2005-19"}]},{"driverAId":"jerome-dambrosio","driverBId":"kimi-raikkonen","sharedEventCount":1,"teams":[{"id":"lotus-f1","name":"Lotus","eventCount":1,"firstSeason":2012,"lastSeason":2012,"firstEventId":"2012-13","lastEventId":"2012-13"}]},{"driverAId":"jerome-dambrosio","driverBId":"timo-glock","sharedEventCount":19,"teams":[{"id":"virgin","name":"Virgin","eventCount":19,"firstSeason":2011,"lastSeason":2011,"firstEventId":"2011-01","lastEventId":"2011-19"}]},{"driverAId":"johnny-herbert","driverBId":"luciano-burti","sharedEventCount":1,"teams":[{"id":"jaguar","name":"Jaguar","eventCount":1,"firstSeason":2000,"lastSeason":2000,"firstEventId":"2000-10","lastEventId":"2000-10"}]},{"driverAId":"jolyon-palmer","driverBId":"kevin-magnussen","sharedEventCount":21,"teams":[{"id":"renault","name":"Renault","eventCount":21,"firstSeason":2016,"lastSeason":2016,"firstEventId":"2016-01","lastEventId":"2016-21"}]},{"driverAId":"jolyon-palmer","driverBId":"nico-hulkenberg","sharedEventCount":16,"teams":[{"id":"renault","name":"Renault","eventCount":16,"firstSeason":2017,"lastSeason":2017,"firstEventId":"2017-01","lastEventId":"2017-16"}]},{"driverAId":"jos-verstappen","driverBId":"justin-wilson","sharedEventCount":11,"teams":[{"id":"minardi","name":"Minardi","eventCount":11,"firstSeason":2003,"lastSeason":2003,"firstEventId":"2003-01","lastEventId":"2003-11"}]},{"driverAId":"jos-verstappen","driverBId":"nicolas-kiesa","sharedEventCount":5,"teams":[{"id":"minardi","name":"Minardi","eventCount":5,"firstSeason":2003,"lastSeason":2003,"firstEventId":"2003-12","lastEventId":"2003-16"}]},{"driverAId":"jos-verstappen","driverBId":"pedro-de-la-rosa","sharedEventCount":17,"teams":[{"id":"arrows","name":"Arrows","eventCount":17,"firstSeason":2000,"lastSeason":2000,"firstEventId":"2000-01","lastEventId":"2000-17"}]},{"driverAId":"juan-pablo-montoya","driverBId":"kimi-raikkonen","sharedEventCount":27,"teams":[{"id":"mclaren","name":"McLaren","eventCount":27,"firstSeason":2005,"lastSeason":2006,"firstEventId":"2005-01","lastEventId":"2006-10"}]},{"driverAId":"juan-pablo-montoya","driverBId":"marc-gene","sharedEventCount":3,"teams":[{"id":"williams","name":"Williams","eventCount":3,"firstSeason":2003,"lastSeason":2004,"firstEventId":"2003-14","lastEventId":"2004-11"}]},{"driverAId":"juan-pablo-montoya","driverBId":"ralf-schumacher","sharedEventCount":61,"teams":[{"id":"williams","name":"Williams","eventCount":61,"firstSeason":2001,"lastSeason":2004,"firstEventId":"2001-01","lastEventId":"2004-18"}]},{"driverAId":"jules-bianchi","driverBId":"max-chilton","sharedEventCount":34,"teams":[{"id":"marussia","name":"Marussia","eventCount":34,"firstSeason":2013,"lastSeason":2014,"firstEventId":"2013-01","lastEventId":"2014-15"}]},{"driverAId":"justin-wilson","driverBId":"mark-webber","sharedEventCount":5,"teams":[{"id":"jaguar","name":"Jaguar","eventCount":5,"firstSeason":2003,"lastSeason":2003,"firstEventId":"2003-12","lastEventId":"2003-16"}]},{"driverAId":"kamui-kobayashi","driverBId":"marcus-ericsson","sharedEventCount":15,"teams":[{"id":"caterham","name":"Caterham","eventCount":15,"firstSeason":2014,"lastSeason":2014,"firstEventId":"2014-01","lastEventId":"2014-16"}]},{"driverAId":"kamui-kobayashi","driverBId":"nick-heidfeld","sharedEventCount":5,"teams":[{"id":"sauber","name":"Sauber","eventCount":5,"firstSeason":2010,"lastSeason":2010,"firstEventId":"2010-15","lastEventId":"2010-19"}]},{"driverAId":"kamui-kobayashi","driverBId":"pedro-de-la-rosa","sharedEventCount":15,"teams":[{"id":"sauber","name":"Sauber","eventCount":15,"firstSeason":2010,"lastSeason":2011,"firstEventId":"2010-01","lastEventId":"2011-07"}]},{"driverAId":"kamui-kobayashi","driverBId":"sergio-perez","sharedEventCount":38,"teams":[{"id":"sauber","name":"Sauber","eventCount":38,"firstSeason":2011,"lastSeason":2012,"firstEventId":"2011-01","lastEventId":"2012-20"}]},{"driverAId":"kamui-kobayashi","driverBId":"will-stevens","sharedEventCount":1,"teams":[{"id":"caterham","name":"Caterham","eventCount":1,"firstSeason":2014,"lastSeason":2014,"firstEventId":"2014-19","lastEventId":"2014-19"}]},{"driverAId":"karun-chandhok","driverBId":"sakon-yamamoto","sharedEventCount":1,"teams":[{"id":"hrt","name":"HRT","eventCount":1,"firstSeason":2010,"lastSeason":2010,"firstEventId":"2010-10","lastEventId":"2010-10"}]},{"driverAId":"kazuki-nakajima","driverBId":"nico-rosberg","sharedEventCount":36,"teams":[{"id":"williams","name":"Williams","eventCount":36,"firstSeason":2007,"lastSeason":2009,"firstEventId":"2007-17","lastEventId":"2009-17"}]},{"driverAId":"kevin-magnussen","driverBId":"mick-schumacher","sharedEventCount":22,"teams":[{"id":"haas","name":"Haas","eventCount":22,"firstSeason":2022,"lastSeason":2022,"firstEventId":"2022-01","lastEventId":"2022-22"}]},{"driverAId":"kevin-magnussen","driverBId":"nico-hulkenberg","sharedEventCount":44,"teams":[{"id":"haas","name":"Haas","eventCount":44,"firstSeason":2023,"lastSeason":2024,"firstEventId":"2023-01","lastEventId":"2024-24"}]},{"driverAId":"kevin-magnussen","driverBId":"pietro-fittipaldi","sharedEventCount":2,"teams":[{"id":"haas","name":"Haas","eventCount":2,"firstSeason":2020,"lastSeason":2020,"firstEventId":"2020-16","lastEventId":"2020-17"}]},{"driverAId":"kevin-magnussen","driverBId":"romain-grosjean","sharedEventCount":77,"teams":[{"id":"haas","name":"Haas","eventCount":77,"firstSeason":2017,"lastSeason":2020,"firstEventId":"2017-01","lastEventId":"2020-15"}]},{"driverAId":"kimi-raikkonen","driverBId":"luca-badoer","sharedEventCount":2,"teams":[{"id":"ferrari","name":"Ferrari","eventCount":2,"firstSeason":2009,"lastSeason":2009,"firstEventId":"2009-11","lastEventId":"2009-12"}]},{"driverAId":"kimi-raikkonen","driverBId":"nick-heidfeld","sharedEventCount":17,"teams":[{"id":"sauber","name":"Sauber","eventCount":17,"firstSeason":2001,"lastSeason":2001,"firstEventId":"2001-01","lastEventId":"2001-17"}]},{"driverAId":"kimi-raikkonen","driverBId":"pedro-de-la-rosa","sharedEventCount":9,"teams":[{"id":"mclaren","name":"McLaren","eventCount":9,"firstSeason":2005,"lastSeason":2006,"firstEventId":"2005-03","lastEventId":"2006-18"}]},{"driverAId":"kimi-raikkonen","driverBId":"romain-grosjean","sharedEventCount":36,"teams":[{"id":"lotus-f1","name":"Lotus","eventCount":36,"firstSeason":2012,"lastSeason":2013,"firstEventId":"2012-01","lastEventId":"2013-17"}]},{"driverAId":"kimi-raikkonen","driverBId":"sebastian-vettel","sharedEventCount":81,"teams":[{"id":"ferrari","name":"Ferrari","eventCount":81,"firstSeason":2015,"lastSeason":2018,"firstEventId":"2015-01","lastEventId":"2018-21"}]},{"driverAId":"lance-stroll","driverBId":"nico-hulkenberg","sharedEventCount":4,"teams":[{"id":"aston-martin","name":"Aston Martin","eventCount":2,"firstSeason":2022,"lastSeason":2022,"firstEventId":"2022-01","lastEventId":"2022-02"},{"id":"racing-point","name":"Racing Point","eventCount":2,"firstSeason":2020,"lastSeason":2020,"firstEventId":"2020-04","lastEventId":"2020-05"}]},{"driverAId":"lance-stroll","driverBId":"paul-di-resta","sharedEventCount":1,"teams":[{"id":"williams","name":"Williams","eventCount":1,"firstSeason":2017,"lastSeason":2017,"firstEventId":"2017-11","lastEventId":"2017-11"}]},{"driverAId":"lance-stroll","driverBId":"sebastian-vettel","sharedEventCount":42,"teams":[{"id":"aston-martin","name":"Aston Martin","eventCount":42,"firstSeason":2021,"lastSeason":2022,"firstEventId":"2021-01","lastEventId":"2022-22"}]},{"driverAId":"lance-stroll","driverBId":"sergey-sirotkin","sharedEventCount":21,"teams":[{"id":"williams","name":"Williams","eventCount":21,"firstSeason":2018,"lastSeason":2018,"firstEventId":"2018-01","lastEventId":"2018-21"}]},{"driverAId":"lance-stroll","driverBId":"sergio-perez","sharedEventCount":35,"teams":[{"id":"racing-point","name":"Racing Point","eventCount":35,"firstSeason":2019,"lastSeason":2020,"firstEventId":"2019-01","lastEventId":"2020-17"}]},{"driverAId":"lando-norris","driverBId":"oscar-piastri","sharedEventCount":80,"teams":[{"id":"mclaren","name":"McLaren","eventCount":80,"firstSeason":2023,"lastSeason":2026,"firstEventId":"2023-01","lastEventId":"2026-10"}]},{"driverAId":"lewis-hamilton","driverBId":"nico-rosberg","sharedEventCount":78,"teams":[{"id":"mercedes","name":"Mercedes","eventCount":78,"firstSeason":2013,"lastSeason":2016,"firstEventId":"2013-01","lastEventId":"2016-21"}]},{"driverAId":"lewis-hamilton","driverBId":"valtteri-bottas","sharedEventCount":100,"teams":[{"id":"mercedes","name":"Mercedes","eventCount":100,"firstSeason":2017,"lastSeason":2021,"firstEventId":"2017-01","lastEventId":"2021-22"}]},{"driverAId":"liam-lawson","driverBId":"max-verstappen","sharedEventCount":2,"teams":[{"id":"red-bull","name":"Red Bull","eventCount":2,"firstSeason":2025,"lastSeason":2025,"firstEventId":"2025-01","lastEventId":"2025-02"}]},{"driverAId":"liam-lawson","driverBId":"yuki-tsunoda","sharedEventCount":11,"teams":[{"id":"alphatauri","name":"AlphaTauri","eventCount":5,"firstSeason":2023,"lastSeason":2023,"firstEventId":"2023-13","lastEventId":"2023-17"},{"id":"rb","name":"RB","eventCount":6,"firstSeason":2024,"lastSeason":2024,"firstEventId":"2024-19","lastEventId":"2024-24"}]},{"driverAId":"lucas-di-grassi","driverBId":"timo-glock","sharedEventCount":19,"teams":[{"id":"virgin","name":"Virgin","eventCount":19,"firstSeason":2010,"lastSeason":2010,"firstEventId":"2010-01","lastEventId":"2010-19"}]},{"driverAId":"marcus-ericsson","driverBId":"pascal-wehrlein","sharedEventCount":18,"teams":[{"id":"sauber","name":"Sauber","eventCount":18,"firstSeason":2017,"lastSeason":2017,"firstEventId":"2017-03","lastEventId":"2017-20"}]},{"driverAId":"mark-webber","driverBId":"nick-heidfeld","sharedEventCount":14,"teams":[{"id":"williams","name":"Williams","eventCount":14,"firstSeason":2005,"lastSeason":2005,"firstEventId":"2005-01","lastEventId":"2005-14"}]},{"driverAId":"mark-webber","driverBId":"nico-rosberg","sharedEventCount":18,"teams":[{"id":"williams","name":"Williams","eventCount":18,"firstSeason":2006,"lastSeason":2006,"firstEventId":"2006-01","lastEventId":"2006-18"}]},{"driverAId":"mark-webber","driverBId":"sebastian-vettel","sharedEventCount":94,"teams":[{"id":"red-bull","name":"Red Bull","eventCount":94,"firstSeason":2009,"lastSeason":2013,"firstEventId":"2009-01","lastEventId":"2013-19"}]},{"driverAId":"max-verstappen","driverBId":"pierre-gasly","sharedEventCount":12,"teams":[{"id":"red-bull","name":"Red Bull","eventCount":12,"firstSeason":2019,"lastSeason":2019,"firstEventId":"2019-01","lastEventId":"2019-12"}]},{"driverAId":"max-verstappen","driverBId":"sergio-perez","sharedEventCount":90,"teams":[{"id":"red-bull","name":"Red Bull","eventCount":90,"firstSeason":2021,"lastSeason":2024,"firstEventId":"2021-01","lastEventId":"2024-24"}]},{"driverAId":"max-verstappen","driverBId":"yuki-tsunoda","sharedEventCount":22,"teams":[{"id":"red-bull","name":"Red Bull","eventCount":22,"firstSeason":2025,"lastSeason":2025,"firstEventId":"2025-03","lastEventId":"2025-24"}]},{"driverAId":"michael-schumacher","driverBId":"nico-rosberg","sharedEventCount":58,"teams":[{"id":"mercedes","name":"Mercedes","eventCount":58,"firstSeason":2010,"lastSeason":2012,"firstEventId":"2010-01","lastEventId":"2012-20"}]},{"driverAId":"michael-schumacher","driverBId":"rubens-barrichello","sharedEventCount":104,"teams":[{"id":"ferrari","name":"Ferrari","eventCount":104,"firstSeason":2000,"lastSeason":2005,"firstEventId":"2000-01","lastEventId":"2005-19"}]},{"driverAId":"mick-schumacher","driverBId":"nikita-mazepin","sharedEventCount":22,"teams":[{"id":"haas","name":"Haas","eventCount":22,"firstSeason":2021,"lastSeason":2021,"firstEventId":"2021-01","lastEventId":"2021-22"}]},{"driverAId":"mika-salo","driverBId":"pedro-diniz","sharedEventCount":17,"teams":[{"id":"sauber","name":"Sauber","eventCount":17,"firstSeason":2000,"lastSeason":2000,"firstEventId":"2000-01","lastEventId":"2000-17"}]},{"driverAId":"narain-karthikeyan","driverBId":"pedro-de-la-rosa","sharedEventCount":20,"teams":[{"id":"hrt","name":"HRT","eventCount":20,"firstSeason":2012,"lastSeason":2012,"firstEventId":"2012-01","lastEventId":"2012-20"}]},{"driverAId":"narain-karthikeyan","driverBId":"tiago-monteiro","sharedEventCount":19,"teams":[{"id":"jordan","name":"Jordan","eventCount":19,"firstSeason":2005,"lastSeason":2005,"firstEventId":"2005-01","lastEventId":"2005-19"}]},{"driverAId":"narain-karthikeyan","driverBId":"vitantonio-liuzzi","sharedEventCount":7,"teams":[{"id":"hrt","name":"HRT","eventCount":7,"firstSeason":2011,"lastSeason":2011,"firstEventId":"2011-02","lastEventId":"2011-08"}]},{"driverAId":"nicholas-latifi","driverBId":"nyck-de-vries","sharedEventCount":1,"teams":[{"id":"williams","name":"Williams","eventCount":1,"firstSeason":2022,"lastSeason":2022,"firstEventId":"2022-16","lastEventId":"2022-16"}]},{"driverAId":"nick-heidfeld","driverBId":"robert-kubica","sharedEventCount":57,"teams":[{"id":"bmw-sauber","name":"BMW Sauber","eventCount":57,"firstSeason":2006,"lastSeason":2009,"firstEventId":"2006-13","lastEventId":"2009-17"}]},{"driverAId":"nick-heidfeld","driverBId":"sebastian-vettel","sharedEventCount":1,"teams":[{"id":"bmw-sauber","name":"BMW Sauber","eventCount":1,"firstSeason":2007,"lastSeason":2007,"firstEventId":"2007-07","lastEventId":"2007-07"}]},{"driverAId":"nick-heidfeld","driverBId":"timo-glock","sharedEventCount":4,"teams":[{"id":"jordan","name":"Jordan","eventCount":4,"firstSeason":2004,"lastSeason":2004,"firstEventId":"2004-08","lastEventId":"2004-18"}]},{"driverAId":"nick-heidfeld","driverBId":"vitaly-petrov","sharedEventCount":11,"teams":[{"id":"renault","name":"Renault","eventCount":11,"firstSeason":2011,"lastSeason":2011,"firstEventId":"2011-01","lastEventId":"2011-11"}]},{"driverAId":"nico-hulkenberg","driverBId":"oliver-bearman","sharedEventCount":2,"teams":[{"id":"haas","name":"Haas","eventCount":2,"firstSeason":2024,"lastSeason":2024,"firstEventId":"2024-17","lastEventId":"2024-21"}]},{"driverAId":"nico-hulkenberg","driverBId":"paul-di-resta","sharedEventCount":20,"teams":[{"id":"force-india","name":"Force India","eventCount":20,"firstSeason":2012,"lastSeason":2012,"firstEventId":"2012-01","lastEventId":"2012-20"}]},{"driverAId":"nico-hulkenberg","driverBId":"rubens-barrichello","sharedEventCount":19,"teams":[{"id":"williams","name":"Williams","eventCount":19,"firstSeason":2010,"lastSeason":2010,"firstEventId":"2010-01","lastEventId":"2010-19"}]},{"driverAId":"nico-hulkenberg","driverBId":"sergio-perez","sharedEventCount":60,"teams":[{"id":"force-india","name":"Force India","eventCount":59,"firstSeason":2014,"lastSeason":2016,"firstEventId":"2014-01","lastEventId":"2016-21"},{"id":"racing-point","name":"Racing Point","eventCount":1,"firstSeason":2020,"lastSeason":2020,"firstEventId":"2020-11","lastEventId":"2020-11"}]},{"driverAId":"nyck-de-vries","driverBId":"yuki-tsunoda","sharedEventCount":10,"teams":[{"id":"alphatauri","name":"AlphaTauri","eventCount":10,"firstSeason":2023,"lastSeason":2023,"firstEventId":"2023-01","lastEventId":"2023-10"}]},{"driverAId":"olivier-panis","driverBId":"ricardo-zonta","sharedEventCount":4,"teams":[{"id":"toyota","name":"Toyota","eventCount":4,"firstSeason":2004,"lastSeason":2004,"firstEventId":"2004-13","lastEventId":"2004-16"}]},{"driverAId":"pascal-wehrlein","driverBId":"rio-haryanto","sharedEventCount":12,"teams":[{"id":"manor","name":"Manor","eventCount":12,"firstSeason":2016,"lastSeason":2016,"firstEventId":"2016-01","lastEventId":"2016-12"}]},{"driverAId":"pastor-maldonado","driverBId":"romain-grosjean","sharedEventCount":38,"teams":[{"id":"lotus-f1","name":"Lotus","eventCount":38,"firstSeason":2014,"lastSeason":2015,"firstEventId":"2014-01","lastEventId":"2015-19"}]},{"driverAId":"pastor-maldonado","driverBId":"rubens-barrichello","sharedEventCount":19,"teams":[{"id":"williams","name":"Williams","eventCount":19,"firstSeason":2011,"lastSeason":2011,"firstEventId":"2011-01","lastEventId":"2011-19"}]},{"driverAId":"pastor-maldonado","driverBId":"valtteri-bottas","sharedEventCount":19,"teams":[{"id":"williams","name":"Williams","eventCount":19,"firstSeason":2013,"lastSeason":2013,"firstEventId":"2013-01","lastEventId":"2013-19"}]},{"driverAId":"pierre-gasly","driverBId":"yuki-tsunoda","sharedEventCount":44,"teams":[{"id":"alphatauri","name":"AlphaTauri","eventCount":44,"firstSeason":2021,"lastSeason":2022,"firstEventId":"2021-01","lastEventId":"2022-22"}]},{"driverAId":"robert-kubica","driverBId":"vitaly-petrov","sharedEventCount":19,"teams":[{"id":"renault","name":"Renault","eventCount":19,"firstSeason":2010,"lastSeason":2010,"firstEventId":"2010-01","lastEventId":"2010-19"}]},{"driverAId":"roberto-merhi","driverBId":"will-stevens","sharedEventCount":14,"teams":[{"id":"marussia","name":"Marussia","eventCount":14,"firstSeason":2015,"lastSeason":2015,"firstEventId":"2015-01","lastEventId":"2015-19"}]},{"driverAId":"sakon-yamamoto","driverBId":"takuma-sato","sharedEventCount":7,"teams":[{"id":"super-aguri","name":"Super Aguri","eventCount":7,"firstSeason":2006,"lastSeason":2006,"firstEventId":"2006-12","lastEventId":"2006-18"}]},{"driverAId":"scott-speed","driverBId":"vitantonio-liuzzi","sharedEventCount":28,"teams":[{"id":"toro-rosso","name":"Toro Rosso","eventCount":28,"firstSeason":2006,"lastSeason":2007,"firstEventId":"2006-01","lastEventId":"2007-10"}]},{"driverAId":"sebastian-vettel","driverBId":"sebastien-bourdais","sharedEventCount":18,"teams":[{"id":"toro-rosso","name":"Toro Rosso","eventCount":18,"firstSeason":2008,"lastSeason":2008,"firstEventId":"2008-01","lastEventId":"2008-18"}]},{"driverAId":"sebastian-vettel","driverBId":"vitantonio-liuzzi","sharedEventCount":7,"teams":[{"id":"toro-rosso","name":"Toro Rosso","eventCount":7,"firstSeason":2007,"lastSeason":2007,"firstEventId":"2007-11","lastEventId":"2007-17"}]},{"driverAId":"sebastien-bourdais","driverBId":"sebastien-buemi","sharedEventCount":9,"teams":[{"id":"toro-rosso","name":"Toro Rosso","eventCount":9,"firstSeason":2009,"lastSeason":2009,"firstEventId":"2009-01","lastEventId":"2009-09"}]},{"driverAId":"sergio-perez","driverBId":"valtteri-bottas","sharedEventCount":10,"teams":[{"id":"cadillac","name":"Cadillac","eventCount":10,"firstSeason":2026,"lastSeason":2026,"firstEventId":"2026-01","lastEventId":"2026-10"}]},{"driverAId":"takuma-sato","driverBId":"yuji-ide","sharedEventCount":4,"teams":[{"id":"super-aguri","name":"Super Aguri","eventCount":4,"firstSeason":2006,"lastSeason":2006,"firstEventId":"2006-01","lastEventId":"2006-04"}]}]}
